jpu/__init__.py
jpu/core.py
jpu/jax_numpy_func.py
jpu/jpu_version.py
jpu/monkey.py
jpu/quantity.py
jpu/registry.py
jpu/numpy/__init__.py
jpu/numpy/__init__.pyi
jpu/numpy/linalg.py
jpu/numpy/linalg.pyi
jpu-0.0.5.dist-info/METADATA
jpu-0.0.5.dist-info/WHEEL
jpu-0.0.5.dist-info/licenses/LICENSE
jpu-0.0.5.dist-info/RECORD
