Metadata-Version: 2.4
Name: jpu
Version: 0.0.5
Summary: JAX + Units
Project-URL: Homepage, https://github.com/dfm/jpu
Project-URL: Source, https://github.com/dfm/jpu
Project-URL: Bug Tracker, https://github.com/dfm/jpu/issues
Author-email: Dan Foreman-Mackey <foreman.mackey@gmail.com>
License: MIT License
License-File: LICENSE
Classifier: Development Status :: 5 - Production/Stable
Classifier: License :: OSI Approved :: MIT License
Classifier: Operating System :: OS Independent
Classifier: Programming Language :: Python :: 3
Requires-Python: >=3.9
Requires-Dist: jax
Requires-Dist: pint
Provides-Extra: test
Requires-Dist: jaxlib; extra == 'test'
Requires-Dist: pytest; extra == 'test'
